aisum/__init__.py
aisum/cli.py
aisum/openai_api.py
aisum/utils.py
tests/__init__.py
tests/test_cli.py
tests/test_openai_api.py
aisum-0.1.2.dist-info/LICENSE
aisum-0.1.2.dist-info/METADATA
aisum-0.1.2.dist-info/WHEEL
aisum-0.1.2.dist-info/entry_points.txt
aisum-0.1.2.dist-info/top_level.txt
aisum-0.1.2.dist-info/RECORD
