Metadata-Version: 2.1
Name: aisum
Version: 0.1.2
Classifier: Programming Language :: Python :: 3
Classifier: License :: OSI Approved :: MIT License
Classifier: Operating System :: OS Independent
Requires-Python: >=3.6
License-File: LICENSE
Requires-Dist: click
Requires-Dist: requests
Requires-Dist: openai
